README.rst
setup.cfg
setup.py
gen4id/__init__.py
gen4id/increase_gen.py
gen4id.egg-info/PKG-INFO
gen4id.egg-info/SOURCES.txt
gen4id.egg-info/dependency_links.txt
gen4id.egg-info/requires.txt
gen4id.egg-info/top_level.txt
test/__init__.py
test/bench.py