Metadata-Version: 2.1
Name: gen4id
Version: 1.0.2
Summary: gen4id a simple but maybe useful package for auto-increment ids 
Home-page: https://github.com/tony-is-coding/gen4id
Author: tony-is-coding
Author-email: newbiwtan@163.com
Maintainer: tony-is-coing
License: UNKNOWN
Platform: UNKNOWN
Classifier: Programming Language :: Python :: 3
Classifier: License :: OSI Approved :: MIT License
Classifier: Operating System :: OS Independent
Provides-Extra: docs
